{"id": 67, "skill": ["なに君 ストーカー？", [["[15 charge]", "Remove 9 random puzzle balls.\n"], ["[14 charge]", "Remove 10 random puzzle balls.\n"], ["[13 charge]", "Remove 11 random puzzle balls.\n"], ["[12 charge]", "Remove 12 random puzzle balls.\n"], ["[11 charge]", "Remove 13 random puzzle balls.\n"]]], "bonus": ["Increase the removal score by 100.\n", "Increase the removal score by 120.\n", "Increase the removal score by 140.\n", "Increase the removal score by 180.\n", "Increase the removal score by 220.\n"], "kirakira": ["Increase the removal score of purple balls by 130.\n", "Increase the removal score of purple balls by 160.\n", "Increase the removal score of purple balls by 190.\n", "Increase the removal score of purple balls by 230.\n", "Increase the removal score of purple balls by 270.\n"], "dokidoki": ["Gain 5 extra seconds with 10% probability when starting the stage.\n", "Gain 5 extra seconds with 20% probability when starting the stage.\n", "Gain 5 extra seconds with 30% probability when starting the stage.\n", "Gain 5 extra seconds with 40% probability when starting the stage.\n", "Gain 5 extra seconds with 50% probability when starting the stage.\n"]}